[{"id": "thecopilot", "username": "TheCoPilot", "online": true, "perfs": {"chess960": {"games": 35, "rating": 1593, "rd": 126, "prog": -345, "prov": true}, "antichess": {"games": 33, "rating": 1227, "rd": 250, "prog": -58, "prov": true}, "atomic": {"games": 4, "rating": 1503, "rd": 288, "prog": 0, "prov": true}, "racingKings": {"games": 5, "rating": 1567, "rd": 187, "prog": 0, "prov": true}, "ultraBullet": {"games": 416, "rating": 1804, "rd": 47, "prog": -4}, "blitz": {"games": 870, "rating": 1960, "rd": 48, "prog": -6}, "kingOfTheHill": {"games": 17, "rating": 1782, "rd": 229, "prog": 128, "prov": true}, "crazyhouse": {"games": 216, "rating": 1776, "rd": 92, "prog": -68}, "threeCheck": {"games": 12, "rating": 1616, "rd": 134, "prog": -64, "prov": true}, "bullet": {"games": 22694, "rating": 1997, "rd": 45, "prog": -21}, "correspondence": {"games": 1, "rating": 1343, "rd": 353, "prog": 0, "prov": true}, "horde": {"games": 15, "rating": 1840, "rd": 151, "prog": 98, "prov": true}, "puzzle": {"games": 146, "rating": 2330, "rd": 168, "prog": 22, "prov": true}, "classical": {"games": 16, "rating": 1806, "rd": 217, "prog": 0, "prov": true}, "rapid": {"games": 45, "rating": 1980, "rd": 79, "prog": 141}, "storm": {"runs": 1, "score": 23}}, "createdAt": 1432907210365, "profile": {"country": "US", "location": "Long Beach, California", "bio": "My name is Rick, aka TheCoPilot, and I absolutely love playing chess. I love playing trash lines, awful attacks, and insane time scrambles. If the game gets the adrenaline pumping, I consider it a win! I stream often and find myself talking smack to anyone and everyone (all in fun of course) and I hope to see you stop by!", "firstName": "Rick", "lastName": "Cozart", "uscfRating": 1861, "links": "Instagram: @rickcozart\r\nTwitch: https://www.twitch.tv/thecopilot"}, "seenAt": 1612476358367, "playTime": {"total": 2541586, "tv": 8695}, "language": "en-US", "url": "https://lichess.org/@/TheCoPilot", "playing": "https://lichess.org/tWBBI9wx/black", "nbFollowing": 14, "nbFollowers": 62, "completionRate": 100, "count": {"all": 24703, "rated": 24393, "ai": 1, "draw": 825, "drawH": 825, "loss": 10678, "lossH": 10677, "win": 13200, "winH": 13200, "bookmark": 0, "playing": 1, "import": 5, "me": 0}, "streaming": true}, {"id": "brokenarrow69", "username": "brokenarrow69", "online": true, "perfs": {"chess960": {"games": 27, "rating": 1423, "rd": 124, "prog": 62, "prov": true}, "antichess": {"games": 14, "rating": 1210, "rd": 132, "prog": -28, "prov": true}, "atomic": {"games": 7, "rating": 1155, "rd": 173, "prog": 0, "prov": true}, "racingKings": {"games": 1, "rating": 1432, "rd": 298, "prog": 0, "prov": true}, "ultraBullet": {"games": 228, "rating": 1226, "rd": 70, "prog": -5}, "blitz": {"games": 4384, "rating": 2013, "rd": 45, "prog": 9}, "kingOfTheHill": {"games": 11, "rating": 1498, "rd": 151, "prog": 0, "prov": true}, "crazyhouse": {"games": 42, "rating": 1682, "rd": 100, "prog": -7}, "bullet": {"games": 1174, "rating": 1911, "rd": 45, "prog": -40}, "correspondence": {"games": 5, "rating": 1796, "rd": 198, "prog": 0, "prov": true}, "horde": {"games": 2, "rating": 1545, "rd": 258, "prog": 0, "prov": true}, "puzzle": {"games": 1338, "rating": 2146, "rd": 70, "prog": 0}, "classical": {"games": 60, "rating": 1928, "rd": 76, "prog": 82}, "rapid": {"games": 908, "rating": 1945, "rd": 46, "prog": 8}, "storm": {"runs": 54, "score": 44}}, "createdAt": 1499776509804, "profile": {"bio": "If one doesn't gambit then how can they live ;_;?"}, "seenAt": 1612476459362, "playTime": {"total": 2512931, "tv": 5753}, "language": "en-US", "url": "https://lichess.org/@/brokenarrow69", "nbFollowing": 26, "nbFollowers": 157, "completionRate": 100, "count": {"all": 8687, "rated": 6870, "ai": 157, "draw": 501, "drawH": 497, "loss": 4215, "lossH": 4100, "win": 3971, "winH": 3933, "bookmark": 0, "playing": 0, "import": 4, "me": 0}, "streaming": true}, {"id": "sednomini", "username": "SedNomini", "online": true, "perfs": {"puzzle": {"games": 1024, "rating": 1861, "rd": 70, "prog": 0}, "blitz": {"games": 2026, "rating": 1523, "rd": 47, "prog": 2}, "threeCheck": {"games": 1, "rating": 1276, "rd": 262, "prog": 0, "prov": true}, "bullet": {"games": 289, "rating": 1229, "rd": 68, "prog": 0}, "correspondence": {"games": 4, "rating": 1428, "rd": 220, "prog": 0, "prov": true}, "classical": {"games": 434, "rating": 1668, "rd": 57, "prog": 38}, "rapid": {"games": 1648, "rating": 1747, "rd": 45, "prog": 8}, "storm": {"runs": 4, "score": 19}}, "createdAt": 1522630704538, "profile": {"country": "US", "location": "New York"}, "seenAt": 1612475970586, "playTime": {"total": 3241900, "tv": 0}, "language": "en-US", "url": "https://lichess.org/@/SedNomini", "playing": "https://lichess.org/PhmKogeV/black", "nbFollowing": 19, "nbFollowers": 146, "completionRate": 97, "count": {"all": 5386, "rated": 4404, "ai": 80, "draw": 325, "drawH": 322, "loss": 2886, "lossH": 2828, "win": 2175, "winH": 2156, "bookmark": 35, "playing": 1, "import": 3, "me": 0}, "streaming": true}, {"id": "gravereaper", "username": "gravereaper", "online": true, "perfs": {"chess960": {"games": 3, "rating": 1961, "rd": 198, "prog": 0, "prov": true}, "puzzle": {"games": 316, "rating": 2403, "rd": 121, "prog": 0, "prov": true}, "ultraBullet": {"games": 39, "rating": 2018, "rd": 92, "prog": 74}, "blitz": {"games": 918, "rating": 2560, "rd": 49, "prog": -22}, "crazyhouse": {"games": 31, "rating": 2290, "rd": 195, "prog": 79, "prov": true}, "threeCheck": {"games": 16, "rating": 2122, "rd": 198, "prog": 79, "prov": true}, "bullet": {"games": 1169, "rating": 2607, "rd": 46, "prog": 6}, "correspondence": {"games": 0, "rating": 1500, "rd": 500, "prog": 0, "prov": true}, "classical": {"games": 0, "rating": 1500, "rd": 500, "prog": 0, "prov": true}, "rapid": {"games": 10, "rating": 2274, "rd": 144, "prog": 0, "prov": true}, "storm": {"runs": 103, "score": 92}}, "createdAt": 1465506692475, "profile": {"country": "DE", "bio": "Opponents? i only see weaklings"}, "seenAt": 1612476934445, "playTime": {"total": 546127, "tv": 50935}, "language": "de-DE", "title": "IM", "url": "https://lichess.org/@/gravereaper", "playing": "https://lichess.org/J4qBgM2b/black", "nbFollowing": 8, "nbFollowers": 90, "completionRate": 100, "count": {"all": 2742, "rated": 2185, "ai": 190, "draw": 151, "drawH": 148, "loss": 847, "lossH": 665, "win": 1744, "winH": 1739, "bookmark": 0, "playing": 1, "import": 0, "me": 0}, "streaming": true}, {"id": "frostypanda28", "username": "frostypanda28", "online": true, "perfs": {"chess960": {"games": 47, "rating": 2074, "rd": 62, "prog": 65}, "antichess": {"games": 2, "rating": 1379, "rd": 342, "prog": 0, "prov": true}, "racingKings": {"games": 2, "rating": 1348, "rd": 308, "prog": 0, "prov": true}, "ultraBullet": {"games": 1427, "rating": 2079, "rd": 45, "prog": -13}, "blitz": {"games": 60, "rating": 2212, "rd": 53, "prog": -8}, "kingOfTheHill": {"games": 10, "rating": 1570, "rd": 151, "prog": 0, "prov": true}, "crazyhouse": {"games": 14, "rating": 1663, "rd": 121, "prog": 86, "prov": true}, "threeCheck": {"games": 26, "rating": 1808, "rd": 93, "prog": 6}, "bullet": {"games": 1023, "rating": 2342, "rd": 45, "prog": 16}, "correspondence": {"games": 3, "rating": 1876, "rd": 245, "prog": 0, "prov": true}, "horde": {"games": 26, "rating": 1954, "rd": 87, "prog": 106}, "puzzle": {"games": 194, "rating": 2131, "rd": 80, "prog": 0}, "classical": {"games": 2, "rating": 1581, "rd": 246, "prog": 0, "prov": true}, "rapid": {"games": 41, "rating": 2116, "rd": 62, "prog": 66}, "storm": {"runs": 27, "score": 54}}, "createdAt": 1608328141198, "profile": {"country": "_rainbow", "bio": "Hey! I'm a big fan of ultra and hyper bullet, while I also enjoy playing longer time controls like Blitz and Rapid. If you wanna play just send me a challenge! Hope to see you around!", "fideRating": 1498}, "seenAt": 1612476244262, "playTime": {"total": 373485, "tv": 5924}, "language": "en-US", "url": "https://lichess.org/@/frostypanda28", "nbFollowing": 36, "nbFollowers": 33, "completionRate": 100, "count": {"all": 4160, "rated": 2685, "ai": 45, "draw": 271, "drawH": 267, "loss": 1510, "lossH": 1487, "win": 2379, "winH": 2361, "bookmark": 0, "playing": 0, "import": 0, "me": 0}}, {"id": "kiezking", "username": "Kiezking", "online": true, "perfs": {"blitz": {"games": 865, "rating": 2482, "rd": 45, "prog": 13}, "horde": {"games": 2, "rating": 1338, "rd": 274, "prog": 0, "prov": true}, "bullet": {"games": 562, "rating": 2471, "rd": 46, "prog": 11}, "correspondence": {"games": 0, "rating": 1500, "rd": 500, "prog": 0, "prov": true}, "classical": {"games": 0, "rating": 1500, "rd": 500, "prog": 0, "prov": true}, "rapid": {"games": 5, "rating": 1745, "rd": 257, "prog": 0, "prov": true}, "storm": {"runs": 12, "score": 67}}, "createdAt": 1595836776782, "profile": {"country": "DE", "location": "Hamburg", "firstName": "Felix", "lastName": "Meißner", "fideRating": 2410, "links": "https://www.twitch.tv/lockdownchess\r\nhttps://www.instagram.com/lockdownchess/\r\nwww.Luiswirdweltmeister.wordpress.com"}, "seenAt": 1612476364980, "playTime": {"total": 303262, "tv": 1975}, "language": "de-DE", "title": "FM", "url": "https://lichess.org/@/Kiezking", "nbFollowing": 122, "nbFollowers": 109, "completionRate": 80, "count": {"all": 1606, "rated": 1437, "ai": 0, "draw": 158, "drawH": 158, "loss": 587, "lossH": 587, "win": 861, "winH": 861, "bookmark": 0, "playing": 0, "import": 0, "me": 0}, "streaming": true}, {"id": "hunschback", "username": "Hunschback", "online": true, "perfs": {"blitz": {"games": 15, "rating": 1571, "rd": 149, "prog": -116, "prov": true}, "puzzle": {"games": 213, "rating": 1828, "rd": 63, "prog": 0}, "bullet": {"games": 0, "rating": 1500, "rd": 500, "prog": 0, "prov": true}, "correspondence": {"games": 0, "rating": 1500, "rd": 500, "prog": 0, "prov": true}, "classical": {"games": 0, "rating": 1500, "rd": 500, "prog": 0, "prov": true}, "rapid": {"games": 24, "rating": 1816, "rd": 72, "prog": 40}}, "createdAt": 1554838976299, "profile": {"country": "US", "location": "Atlanta", "firstName": "John", "lastName": "Hunschofsky", "links": "twitch.tv/hunschback"}, "seenAt": 1612476602449, "playTime": {"total": 27223, "tv": 41}, "language": "en-US", "url": "https://lichess.org/@/Hunschback", "playing": "https://lichess.org/JPGbeMDa/white", "nbFollowing": 0, "nbFollowers": 0, "completionRate": 100, "count": {"all": 54, "rated": 39, "ai": 11, "draw": 1, "drawH": 0, "loss": 32, "lossH": 23, "win": 21, "winH": 20, "bookmark": 0, "playing": 1, "import": 0, "me": 0}, "streaming": true}, {"id": "angelitort", "username": "AngelitoRT", "online": true, "perfs": {"chess960": {"games": 17, "rating": 2420, "rd": 157, "prog": 32, "prov": true}, "puzzle": {"games": 20, "rating": 2147, "rd": 193, "prog": 61, "prov": true}, "blitz": {"games": 852, "rating": 2682, "rd": 46, "prog": 14}, "kingOfTheHill": {"games": 8, "rating": 1797, "rd": 166, "prog": 0, "prov": true}, "threeCheck": {"games": 17, "rating": 2062, "rd": 149, "prog": 72, "prov": true}, "bullet": {"games": 1287, "rating": 2903, "rd": 45, "prog": 20}, "correspondence": {"games": 0, "rating": 1500, "rd": 500, "prog": 0, "prov": true}, "classical": {"games": 1, "rating": 1317, "rd": 295, "prog": 0, "prov": true}, "rapid": {"games": 2, "rating": 1050, "rd": 249, "prog": 0, "prov": true}, "storm": {"runs": 50, "score": 83}}, "createdAt": 1587931801058, "profile": {"country": "PE", "location": "Trujillo", "bio": "2581 FIDE RATING BLITZ!\r\nSigueme en: https://www.twitch.tv/rterryl", "firstName": "Renato Alfredo", "lastName": "Terry Lujan", "fideRating": 2504, "links": "Facebook: https://www.facebook.com/renatoalfredo.terrylujan.5    Twich:  https://www.twitch.tv/rterryl"}, "seenAt": 1612476824995, "playTime": {"total": 449449, "tv": 50143}, "language": "es-ES", "title": "IM", "url": "https://lichess.org/@/AngelitoRT", "playing": "https://lichess.org/5M6h17G5/white", "nbFollowing": 0, "nbFollowers": 507, "completionRate": 70, "count": {"all": 2269, "rated": 2184, "ai": 0, "draw": 177, "drawH": 177, "loss": 452, "lossH": 452, "win": 1640, "winH": 1640, "bookmark": 0, "playing": 11, "import": 0, "me": 0}, "streaming": true}, {"id": "hockeyboss2929", "username": "hockeyboss2929", "online": true, "perfs": {"puzzle": {"games": 929, "rating": 1986, "rd": 190, "prog": -4, "prov": true}, "ultraBullet": {"games": 1, "rating": 1271, "rd": 308, "prog": 0, "prov": true}, "blitz": {"games": 1490, "rating": 1660, "rd": 45, "prog": 43}, "crazyhouse": {"games": 1, "rating": 1500, "rd": 324, "prog": 0, "prov": true}, "bullet": {"games": 162, "rating": 1517, "rd": 45, "prog": -18}, "correspondence": {"games": 0, "rating": 1500, "rd": 500, "prog": 0, "prov": true}, "classical": {"games": 13, "rating": 1710, "rd": 123, "prog": -69, "prov": true}, "rapid": {"games": 124, "rating": 1666, "rd": 47, "prog": 2}, "storm": {"runs": 23, "score": 35}}, "createdAt": 1534533086030, "profile": {"bio": "$215 in earnings\r\nhttps://www.twitch.tv/faintddog \r\nFollow meeeeeeeeeeeeeeeee", "firstName": "Devin", "lastName": "Scanlon", "uscfRating": 1500, "links": "https://www.twitch.tv/faintddog"}, "seenAt": 1612476717590, "playTime": {"total": 589319, "tv": 0}, "language": "en-US", "url": "https://lichess.org/@/hockeyboss2929", "playing": "https://lichess.org/5Bnh6clt/black", "nbFollowing": 50, "nbFollowers": 31, "completionRate": 97, "count": {"all": 1877, "rated": 1791, "ai": 2, "draw": 88, "drawH": 88, "loss": 917, "lossH": 916, "win": 872, "winH": 871, "bookmark": 2, "playing": 1, "import": 0, "me": 0}, "streaming": true}, {"id": "tuxmanischertiger", "username": "tuxmanischerTiger", "online": true, "perfs": {"blitz": {"games": 111, "rating": 1334, "rd": 46, "prog": 19}, "puzzle": {"games": 3359, "rating": 1951, "rd": 85, "prog": 0}, "bullet": {"games": 357, "rating": 1305, "rd": 45, "prog": -8}, "correspondence": {"games": 0, "rating": 1500, "rd": 500, "prog": 0, "prov": true}, "classical": {"games": 53, "rating": 1725, "rd": 62, "prog": 22}, "rapid": {"games": 53, "rating": 1530, "rd": 59, "prog": 11}, "storm": {"runs": 32, "score": 28}}, "createdAt": 1606928105643, "profile": {"country": "DE", "bio": "see my full progress here:\r\nhttps://chess.keinerspieltmitmir.de/", "firstName": "Robert"}, "seenAt": 1612476918412, "playTime": {"total": 357378, "tv": 313}, "language": "en-US", "url": "https://lichess.org/@/tuxmanischerTiger", "playing": "https://lichess.org/dFUkRrh9/white", "nbFollowing": 34, "nbFollowers": 42, "completionRate": 100, "count": {"all": 938, "rated": 575, "ai": 8, "draw": 34, "drawH": 34, "loss": 432, "lossH": 424, "win": 472, "winH": 472, "bookmark": 2, "playing": 1, "import": 185, "me": 0}, "streaming": true}, {"id": "nextskiller", "username": "NextSkiller", "online": true, "perfs": {"chess960": {"games": 2, "rating": 1476, "rd": 271, "prog": 0, "prov": true}, "atomic": {"games": 4, "rating": 1327, "rd": 251, "prog": 0, "prov": true}, "ultraBullet": {"games": 2, "rating": 1279, "rd": 266, "prog": 0, "prov": true}, "blitz": {"games": 48, "rating": 1186, "rd": 62, "prog": 7}, "kingOfTheHill": {"games": 5, "rating": 1208, "rd": 233, "prog": 0, "prov": true}, "crazyhouse": {"games": 28, "rating": 1312, "rd": 128, "prog": 164, "prov": true}, "bullet": {"games": 54, "rating": 1399, "rd": 98, "prog": 3}, "correspondence": {"games": 13, "rating": 1665, "rd": 140, "prog": 1, "prov": true}, "horde": {"games": 2, "rating": 1279, "rd": 269, "prog": 0, "prov": true}, "puzzle": {"games": 4267, "rating": 1678, "rd": 64, "prog": 0}, "classical": {"games": 775, "rating": 1613, "rd": 45, "prog": -30}, "rapid": {"games": 137, "rating": 1383, "rd": 47, "prog": 4}, "storm": {"runs": 15, "score": 25}}, "createdAt": 1594145387217, "profile": {"links": "https://www.twitch.tv/nextskiller"}, "seenAt": 1612476404781, "playTime": {"total": 1018512, "tv": 141}, "language": "de-DE", "url": "https://lichess.org/@/NextSkiller", "playing": "https://lichess.org/vKilgbHN/white", "nbFollowing": 11, "nbFollowers": 25, "completionRate": 100, "count": {"all": 1545, "rated": 1070, "ai": 31, "draw": 95, "drawH": 95, "loss": 848, "lossH": 828, "win": 602, "winH": 591, "bookmark": 0, "playing": 1, "import": 0, "me": 0}, "streaming": true}, {"id": "chesshobbits99", "username": "ChessHobbits99", "online": true, "perfs": {"chess960": {"games": 11, "rating": 2082, "rd": 113, "prog": 0, "prov": true}, "antichess": {"games": 5, "rating": 1528, "rd": 218, "prog": 0, "prov": true}, "atomic": {"games": 14, "rating": 1774, "rd": 107, "prog": -79}, "racingKings": {"games": 7, "rating": 1895, "rd": 194, "prog": 0, "prov": true}, "ultraBullet": {"games": 86, "rating": 1802, "rd": 60, "prog": 59}, "blitz": {"games": 4131, "rating": 2515, "rd": 45, "prog": -9}, "kingOfTheHill": {"games": 19, "rating": 1857, "rd": 91, "prog": 107}, "crazyhouse": {"games": 31, "rating": 2233, "rd": 85, "prog": 101}, "threeCheck": {"games": 17, "rating": 2182, "rd": 106, "prog": 8}, "bullet": {"games": 1127, "rating": 2603, "rd": 45, "prog": -11}, "correspondence": {"games": 0, "rating": 1500, "rd": 500, "prog": 0, "prov": true}, "horde": {"games": 6, "rating": 1965, "rd": 176, "prog": 0, "prov": true}, "puzzle": {"games": 470, "rating": 2467, "rd": 72, "prog": 0}, "classical": {"games": 16, "rating": 2167, "rd": 116, "prog": 6, "prov": true}, "rapid": {"games": 16, "rating": 2238, "rd": 124, "prog": 43, "prov": true}, "storm": {"runs": 95, "score": 79}}, "createdAt": 1589324329030, "profile": {"country": "DE", "bio": "IM Adrian Gschnitzer und FM Marco Riehle\r\nStreamingaccount\r\nJoin the Team: https://lichess.org/team/chesshobbits99\r\nFolgt uns auf https://www.twitch.tv/chesshobbits99  So verpasst Ihr keinen Stream\r\nIhr findet uns auch auf https://www.youtube.com/channel/UCdOGLy-MJrndM7Fwa2F2RmA\r\n", "firstName": "Marco ", "lastName": "Riehle", "links": "https://m.twitch.tv/chesshobbits99/profile\r\nhttps://www.youtube.com/channel/UCdOGLy-MJrndM7Fwa2F2RmA"}, "seenAt": 1612476811469, "playTime": {"total": 1707640, "tv": 31454}, "language": "de-DE", "title": "IM", "url": "https://lichess.org/@/ChessHobbits99", "nbFollowing": 14, "nbFollowers": 492, "completionRate": 100, "count": {"all": 6036, "rated": 5487, "ai": 7, "draw": 438, "drawH": 438, "loss": 1764, "lossH": 1758, "win": 3834, "winH": 3833, "bookmark": 0, "playing": 0, "import": 0, "me": 0}, "streaming": true}, {"id": "cuajada_zero", "username": "Cuajada_Zero", "online": true, "perfs": {"chess960": {"games": 2, "rating": 1979, "rd": 297, "prog": 0, "prov": true}, "antichess": {"games": 1, "rating": 1624, "rd": 384, "prog": 0, "prov": true}, "horde": {"games": 2, "rating": 1449, "rd": 274, "prog": 0, "prov": true}, "atomic": {"games": 1, "rating": 1730, "rd": 290, "prog": 0, "prov": true}, "racingKings": {"games": 1, "rating": 1258, "rd": 398, "prog": 0, "prov": true}, "blitz": {"games": 118, "rating": 2313, "rd": 45, "prog": 4}, "kingOfTheHill": {"games": 1, "rating": 2200, "rd": 443, "prog": 0, "prov": true}, "crazyhouse": {"games": 2, "rating": 1781, "rd": 242, "prog": 0, "prov": true}, "threeCheck": {"games": 2, "rating": 1963, "rd": 250, "prog": 0, "prov": true}, "bullet": {"games": 141, "rating": 2314, "rd": 48, "prog": 3}, "correspondence": {"games": 0, "rating": 1500, "rd": 500, "prog": 0, "prov": true}, "classical": {"games": 0, "rating": 1500, "rd": 500, "prog": 0, "prov": true}, "rapid": {"games": 4, "rating": 2068, "rd": 184, "prog": 0, "prov": true}, "storm": {"runs": 9, "score": 46}}, "createdAt": 1595445224570, "profile": {"country": "ES", "bio": "Sígueme en // Follow me in Youtube Club de Ajedrez Dama Negra", "links": "https://www.youtube.com/channel/UCQKEuLHbFKtUSxv965_H9nQ\r\nhttps://www.facebook.com/clubajedrezdamanegraonline\r\nhttps://www.twitch.tv/clubajedrezdamanegra\r\nhttps://www.instagram.com/clubajedrezdamanegraonline/"}, "seenAt": 1612476867769, "playTime": {"total": 73923, "tv": 442}, "language": "es-ES", "title": "CM", "url": "https://lichess.org/@/Cuajada_Zero", "playing": "https://lichess.org/HSQqSeCa/black", "nbFollowing": 17, "nbFollowers": 53, "completionRate": 97, "count": {"all": 293, "rated": 275, "ai": 0, "draw": 12, "drawH": 12, "loss": 80, "lossH": 80, "win": 201, "winH": 201, "bookmark": 0, "playing": 1, "import": 0, "me": 0}, "streaming": true}, {"id": "twitch_tv_kugelbuch", "username": "Twitch_tv_KugelBuch", "online": true, "perfs": {"puzzle": {"games": 1189, "rating": 1961, "rd": 63, "prog": 0}, "ultraBullet": {"games": 52, "rating": 1367, "rd": 79, "prog": -21}, "blitz": {"games": 2001, "rating": 1646, "rd": 45, "prog": -3}, "kingOfTheHill": {"games": 1, "rating": 1662, "rd": 298, "prog": 0, "prov": true}, "bullet": {"games": 562, "rating": 1471, "rd": 45, "prog": -11}, "correspondence": {"games": 0, "rating": 1500, "rd": 500, "prog": 0, "prov": true}, "classical": {"games": 4, "rating": 1459, "rd": 222, "prog": 0, "prov": true}, "rapid": {"games": 1555, "rating": 1853, "rd": 45, "prog": 12}, "storm": {"runs": 86, "score": 38}}, "createdAt": 1591843399796, "profile": {"fideRating": 2650, "uscfRating": 2500}, "seenAt": 1612476023959, "playTime": {"total": 2637937, "tv": 0}, "language": "de-DE", "url": "https://lichess.org/@/Twitch_tv_KugelBuch", "playing": "https://lichess.org/DT7BNhT5/white", "nbFollowing": 9, "nbFollowers": 975, "completionRate": 90, "count": {"all": 5494, "rated": 4177, "ai": 28, "draw": 227, "drawH": 227, "loss": 2688, "lossH": 2664, "win": 2579, "winH": 2575, "bookmark": 18, "playing": 1, "import": 0, "me": 0}, "streaming": true}, {"id": "princesschess64", "username": "princesschess64", "online": true, "perfs": {"blitz": {"games": 269, "rating": 2128, "rd": 54, "prog": 1}, "puzzle": {"games": 15757, "rating": 2292, "rd": 62, "prog": 0}, "ultraBullet": {"games": 4, "rating": 1286, "rd": 182, "prog": 0, "prov": true}, "bullet": {"games": 910, "rating": 1926, "rd": 47, "prog": 5}, "correspondence": {"games": 24, "rating": 2049, "rd": 93, "prog": -26}, "classical": {"games": 13, "rating": 1803, "rd": 148, "prog": 82, "prov": true}, "rapid": {"games": 155, "rating": 2088, "rd": 56, "prog": 24}, "storm": {"runs": 2, "score": 47}}, "createdAt": 1468687794040, "profile": {"country": "US", "location": "North Carolina", "bio": "Member of Jacksonville Chess Club in North Carolina.\r\n\r\nMy chess blog resides at https://www.chess.com/blog/PrincessChess", "firstName": "Sara ", "lastName": "Walsh", "fideRating": 1775, "uscfRating": 1875, "links": "https://mobile.twitter.com/princesschess\r\nhttps://m.facebook.com/PrincessChess\r\nhttps://www.chess.com/member/princesschess"}, "seenAt": 1612476390042, "playTime": {"total": 779115, "tv": 0}, "language": "en-GB", "url": "https://lichess.org/@/princesschess64", "nbFollowing": 1, "nbFollowers": 40, "completionRate": 97, "count": {"all": 1779, "rated": 1375, "ai": 16, "draw": 122, "drawH": 122, "loss": 722, "lossH": 717, "win": 935, "winH": 924, "bookmark": 8, "playing": 0, "import": 2, "me": 0}, "streaming": true}, {"id": "hard-defender", "username": "Hard-Defender", "online": true, "perfs": {"chess960": {"games": 27, "rating": 1731, "rd": 88, "prog": 73}, "puzzle": {"games": 2885, "rating": 2277, "rd": 78, "prog": 0}, "ultraBullet": {"games": 2962, "rating": 1567, "rd": 45, "prog": 13}, "blitz": {"games": 960, "rating": 2038, "rd": 45, "prog": -19}, "kingOfTheHill": {"games": 2, "rating": 1162, "rd": 274, "prog": 0, "prov": true}, "crazyhouse": {"games": 30, "rating": 1677, "rd": 203, "prog": -79, "prov": true}, "bullet": {"games": 14324, "rating": 2157, "rd": 64, "prog": 17}, "correspondence": {"games": 48, "rating": 2050, "rd": 75, "prog": -16}, "classical": {"games": 489, "rating": 2346, "rd": 45, "prog": -4}, "rapid": {"games": 245, "rating": 2325, "rd": 57, "prog": 23}, "storm": {"runs": 63, "score": 39}}, "createdAt": 1442936943716, "profile": {"country": "DE", "location": "Borkum", "bio": "Hi, I am a passionate chess player.\r\nMy highest ratings: ELO 1956 / Nat. 2093", "firstName": "ag", "lastName": "R-P. Reinhard", "links": "https://www.facebook.com/rp.reinhard\r\nhttps://www.twitch.tv/hard_defender"}, "seenAt": 1612472136790, "patron": true, "playTime": {"total": 4726673, "tv": 96132}, "language": "de-DE", "url": "https://lichess.org/@/Hard-Defender", "playing": "https://lichess.org/Dh2Wq2Mz/white", "nbFollowing": 92, "nbFollowers": 153, "completionRate": 87, "count": {"all": 27642, "rated": 19095, "ai": 22, "draw": 732, "drawH": 731, "loss": 9710, "lossH": 9694, "win": 17200, "winH": 17195, "bookmark": 3, "playing": 10, "import": 2, "me": 0}, "streaming": true}, {"id": "drdottie", "username": "DrDottie", "online": true, "perfs": {"chess960": {"games": 18, "rating": 1933, "rd": 117, "prog": 149, "prov": true}, "blitz": {"games": 805, "rating": 2212, "rd": 45, "prog": -15}, "puzzle": {"games": 99, "rating": 2431, "rd": 79, "prog": 0}, "bullet": {"games": 169, "rating": 2218, "rd": 51, "prog": 62}, "correspondence": {"games": 0, "rating": 1500, "rd": 500, "prog": 0, "prov": true}, "classical": {"games": 1, "rating": 1958, "rd": 323, "prog": 0, "prov": true}, "rapid": {"games": 101, "rating": 2298, "rd": 45, "prog": 4}, "storm": {"runs": 29, "score": 55}}, "createdAt": 1561823821679, "seenAt": 1612476906960, "playTime": {"total": 397014, "tv": 2111}, "language": "it-IT", "url": "https://lichess.org/@/DrDottie", "playing": "https://lichess.org/cHk7ta5j/black", "nbFollowing": 3, "nbFollowers": 10, "completionRate": 100, "count": {"all": 1159, "rated": 1094, "ai": 0, "draw": 67, "drawH": 67, "loss": 448, "lossH": 448, "win": 644, "winH": 644, "bookmark": 0, "playing": 1, "import": 0, "me": 0}, "streaming": true}, {"id": "destruction_ow", "username": "Destruction_ow", "online": false, "perfs": {"blitz": {"games": 151, "rating": 1183, "rd": 45, "prog": -9}, "puzzle": {"games": 379, "rating": 1773, "rd": 66, "prog": 0}, "bullet": {"games": 12, "rating": 1244, "rd": 148, "prog": -10, "prov": true}, "correspondence": {"games": 0, "rating": 1500, "rd": 500, "prog": 0, "prov": true}, "classical": {"games": 0, "rating": 1500, "rd": 500, "prog": 0, "prov": true}, "rapid": {"games": 805, "rating": 1487, "rd": 47, "prog": 24}}, "createdAt": 1591735094469, "profile": {"country": "US", "firstName": "Jarrod", "lastName": "Schneider", "links": "https://www.twitch.tv/destruction_ow"}, "seenAt": 1612475527341, "playTime": {"total": 873128, "tv": 393}, "language": "en-US", "url": "https://lichess.org/@/Destruction_ow", "nbFollowing": 9, "nbFollowers": 13, "completionRate": 100, "count": {"all": 1461, "rated": 968, "ai": 0, "draw": 70, "drawH": 70, "loss": 752, "lossH": 752, "win": 639, "winH": 639, "bookmark": 0, "playing": 0, "import": 0, "me": 0}}, {"id": "aborigen100500", "username": "Aborigen100500", "online": true, "perfs": {"chess960": {"games": 82, "rating": 2114, "rd": 92, "prog": 21}, "puzzle": {"games": 94, "rating": 2600, "rd": 172, "prog": 56, "prov": true}, "atomic": {"games": 1, "rating": 1453, "rd": 343, "prog": 0, "prov": true}, "blitz": {"games": 8931, "rating": 2634, "rd": 45, "prog": 32}, "kingOfTheHill": {"games": 10, "rating": 1731, "rd": 189, "prog": 0, "prov": true}, "bullet": {"games": 3156, "rating": 2487, "rd": 56, "prog": 31}, "correspondence": {"games": 0, "rating": 1500, "rd": 500, "prog": 0, "prov": true}, "classical": {"games": 1, "rating": 1674, "rd": 281, "prog": 0, "prov": true}, "rapid": {"games": 750, "rating": 2537, "rd": 80, "prog": 55}, "storm": {"runs": 3, "score": 65}}, "createdAt": 1511838731210, "profile": {"country": "UA", "location": "Харьков", "bio": "https://drive.google.com/open?id=1YQHUlkj742hMmWlS-DKrARcLTs0Hx015fv86YGTNsQw\r\nhttps://drive.google.com/open?id=1M8N0ZCR30xVkMeIF7IvuEJnPuaUzwDRH-2PpcUBtUfY\r\nhttps://drive.google.com/open?id=1aYAoOr1Bu8GEgJOe5T6X07f6XutxGI-a8SQBCbOpykY\r\nhttps://drive.google.com/open?id=1PG5ZuZoByeoyZ40XGniTNoJk7o9rZdm3XebKxChUukM\r\nhttps://drive.google.com/open?id=1aotTHcW6w-KuffQR1SPTEwMX3CcmiY9xqEUXnFW-CRk\r\nhttps://www.youtube.com/channel/UCI3x1Nf_WPNBczR55jhjW8g?view_as=subscriber\r\nhttp://www.donationalerts.ru/r/alex_yarovinsky", "firstName": "Алексей", "lastName": "Яровинский", "links": "https://www.facebook.com/alex.yarovinsky\r\nhttps://www.facebook.com/groups/246155952667493/\r\nhttps://www.chess.com/member/aborigen_came"}, "seenAt": 1612476635843, "playTime": {"total": 9970908, "tv": 850211}, "language": "ru-RU", "title": "NM", "url": "https://lichess.org/@/Aborigen100500", "playing": "https://lichess.org/wP7MS1R7/black", "nbFollowing": 176, "nbFollowers": 1433, "completionRate": 93, "count": {"all": 21295, "rated": 12933, "ai": 2, "draw": 2244, "drawH": 2243, "loss": 5976, "lossH": 5975, "win": 13075, "winH": 13075, "bookmark": 0, "playing": 1, "import": 1, "me": 0}, "streaming": true}, {"id": "ehenkes", "username": "ehenkes", "online": true, "perfs": {"chess960": {"games": 66, "rating": 1656, "rd": 89, "prog": 25}, "blitz": {"games": 5557, "rating": 2042, "rd": 45, "prog": 4}, "antichess": {"games": 3, "rating": 1199, "rd": 194, "prog": 0, "prov": true}, "puzzle": {"games": 791, "rating": 2669, "rd": 88, "prog": 0}, "atomic": {"games": 75, "rating": 1090, "rd": 52, "prog": 13}, "ultraBullet": {"games": 13, "rating": 1512, "rd": 140, "prog": -94, "prov": true}, "bullet": {"games": 7628, "rating": 1899, "rd": 45, "prog": 11}, "correspondence": {"games": 0, "rating": 1500, "rd": 500, "prog": 0, "prov": true}, "classical": {"games": 1, "rating": 1667, "rd": 354, "prog": 0, "prov": true}, "rapid": {"games": 234, "rating": 2106, "rd": 58, "prog": -5}, "storm": {"runs": 11, "score": 33}}, "createdAt": 1563284489226, "profile": {"country": "DE", "location": "Einhausen", "bio": "Stream: https://twitch.tv/prettyhardy\r\n\r\nFeel free to ask me questions. With this account, usually, I stream on my channel twitch.tv/prettyhardy on twitch. Have a good time and enjoy the game.\r\nStellt gerne Fragen an mich. Mit Lichess streame ich auf meinem Kanal twitch.tv/prettyhardy bei Twitch. Genießt die Zeit und das Spiel.\r\n\r\nVereinsspieler (Wormser Schachverein), virtuell: SK Laudenbach\r\nStreamer", "firstName": "Erhard", "lastName": "Henkes, Dr.", "fideRating": 1803, "links": "https://www.henkessoft.de/Schach/Schach.html\r\nhttps://twitch.tv/prettyhardy"}, "seenAt": 1612473682774, "playTime": {"total": 3107731, "tv": 5055}, "language": "de-DE", "url": "https://lichess.org/@/ehenkes", "nbFollowing": 101, "nbFollowers": 57, "completionRate": 93, "count": {"all": 13879, "rated": 13585, "ai": 63, "draw": 923, "drawH": 918, "loss": 6339, "lossH": 6301, "win": 6617, "winH": 6597, "bookmark": 0, "playing": 0, "import": 0, "me": 0}, "streaming": true}, {"id": "philipphumburg", "username": "PhilippHumburg", "online": false, "perfs": {"blitz": {"games": 118, "rating": 2087, "rd": 45, "prog": -13}, "puzzle": {"games": 6, "rating": 1996, "rd": 156, "prog": 0, "prov": true}, "atomic": {"games": 3, "rating": 1433, "rd": 245, "prog": 0, "prov": true}, "bullet": {"games": 9, "rating": 2185, "rd": 117, "prog": 0, "prov": true}, "correspondence": {"games": 0, "rating": 1500, "rd": 500, "prog": 0, "prov": true}, "classical": {"games": 1, "rating": 1914, "rd": 311, "prog": 0, "prov": true}, "rapid": {"games": 10, "rating": 1964, "rd": 134, "prog": 0, "prov": true}, "storm": {"runs": 1, "score": 51}}, "createdAt": 1611242297535, "seenAt": 1612475436940, "playTime": {"total": 94970, "tv": 0}, "language": "de-DE", "url": "https://lichess.org/@/PhilippHumburg", "nbFollowing": 3, "nbFollowers": 20, "completionRate": 80, "count": {"all": 231, "rated": 141, "ai": 15, "draw": 6, "drawH": 6, "loss": 56, "lossH": 41, "win": 169, "winH": 169, "bookmark": 0, "playing": 0, "import": 0, "me": 0}}, {"id": "arkadijnaiditsch", "username": "ArkadijNaiditsch", "online": true, "perfs": {"blitz": {"games": 1116, "rating": 2693, "rd": 45, "prog": -27}, "puzzle": {"games": 518, "rating": 2687, "rd": 108, "prog": -70}, "bullet": {"games": 0, "rating": 1500, "rd": 500, "prog": 0, "prov": true}, "correspondence": {"games": 0, "rating": 1500, "rd": 500, "prog": 0, "prov": true}, "classical": {"games": 0, "rating": 1500, "rd": 500, "prog": 0, "prov": true}, "rapid": {"games": 0, "rating": 1500, "rd": 500, "prog": 0, "prov": true}, "storm": {"runs": 33, "score": 73}}, "createdAt": 1602174414707, "profile": {"country": "DE", "bio": "Born on 25.10.1985 in Riga, Latvia. Since 1995 living in Germany.  3 times European Champion, best ELO 2737. Languages spoken : German, Russian, English.  \r\nCEO of Chess Evolution Kft www.chess-evolution.com", "firstName": "GM Arkadij Naiditsch", "fideRating": 2649, "links": "https://www.facebook.com/arkadij.naiditsch \r\nhttps://www.instagram.com/arkadijnaiditsch\r\nhttps://twitter.com/naiditsch"}, "seenAt": 1612476226301, "playTime": {"total": 488756, "tv": 35605}, "language": "en-US", "title": "GM", "url": "https://lichess.org/@/ArkadijNaiditsch", "playing": "https://lichess.org/dMnn8Ivg/black", "nbFollowing": 0, "nbFollowers": 1038, "completionRate": 93, "count": {"all": 1177, "rated": 1117, "ai": 0, "draw": 94, "drawH": 94, "loss": 311, "lossH": 311, "win": 772, "winH": 772, "bookmark": 0, "playing": 1, "import": 4, "me": 0}, "streaming": true}, {"id": "gunnyfeels", "username": "GunnyFeels", "online": true, "perfs": {"chess960": {"games": 5, "rating": 1843, "rd": 186, "prog": 0, "prov": true}, "blitz": {"games": 416, "rating": 2002, "rd": 53, "prog": 31}, "puzzle": {"games": 224, "rating": 2337, "rd": 128, "prog": -150, "prov": true}, "bullet": {"games": 2887, "rating": 1832, "rd": 57, "prog": -15}, "correspondence": {"games": 0, "rating": 1500, "rd": 500, "prog": 0, "prov": true}, "classical": {"games": 0, "rating": 1500, "rd": 500, "prog": 0, "prov": true}, "rapid": {"games": 25, "rating": 2156, "rd": 104, "prog": -62}, "storm": {"runs": 1, "score": 29}}, "createdAt": 1546277069802, "profile": {"country": "DE", "bio": "Bekommen, was man sich wünscht, ist Erfolg. Sich wünschen, was man bekommen kann, ist Glück", "links": "https://www.youtube.com/channel/UCTRQ6W4Wo6tSl-2clB1YE0w\r\nhttps://www.twitch.tv/gunnysworld\r\nhttps://twitter.com/gunny_hs"}, "seenAt": 1612473579167, "playTime": {"total": 1417154, "tv": 624}, "language": "de-DE", "url": "https://lichess.org/@/GunnyFeels", "nbFollowing": 58, "nbFollowers": 158, "completionRate": 100, "count": {"all": 4248, "rated": 3337, "ai": 0, "draw": 295, "drawH": 295, "loss": 1924, "lossH": 1924, "win": 2029, "winH": 2029, "bookmark": 0, "playing": 0, "import": 1, "me": 0}, "streaming": true}, {"id": "chesstourscl", "username": "ChessTourSCL", "online": true, "perfs": {"blitz": {"games": 143, "rating": 2069, "rd": 55, "prog": 18}, "puzzle": {"games": 136, "rating": 2319, "rd": 77, "prog": 0}, "bullet": {"games": 511, "rating": 2033, "rd": 48, "prog": 4}, "correspondence": {"games": 0, "rating": 1500, "rd": 500, "prog": 0, "prov": true}, "classical": {"games": 0, "rating": 1500, "rd": 500, "prog": 0, "prov": true}, "rapid": {"games": 0, "rating": 1500, "rd": 500, "prog": 0, "prov": true}, "storm": {"runs": 1, "score": 23}}, "createdAt": 1563166494935, "profile": {"country": "CL", "links": "https://www.youtube.com/c/CHESSTOUR\r\n\r\nhttps://www.facebook.com/pg/chesstoureventosajedrecisticos\r\n\r\nhttps://www.instagram.com/chesstour/"}, "seenAt": 1612475654521, "playTime": {"total": 204136, "tv": 0}, "language": "es-ES", "url": "https://lichess.org/@/ChessTourSCL", "nbFollowing": 0, "nbFollowers": 50, "completionRate": 97, "count": {"all": 762, "rated": 654, "ai": 2, "draw": 43, "drawH": 43, "loss": 279, "lossH": 279, "win": 440, "winH": 438, "bookmark": 1, "playing": 0, "import": 1, "me": 0}, "streaming": true}, {"id": "susik_gaboyan", "username": "Susik_Gaboyan", "online": true, "perfs": {"chess960": {"games": 9, "rating": 1954, "rd": 152, "prog": 0, "prov": true}, "antichess": {"games": 34, "rating": 1526, "rd": 91, "prog": 52}, "atomic": {"games": 4, "rating": 1264, "rd": 218, "prog": 0, "prov": true}, "racingKings": {"games": 1, "rating": 1191, "rd": 325, "prog": 0, "prov": true}, "ultraBullet": {"games": 7, "rating": 1645, "rd": 177, "prog": 0, "prov": true}, "blitz": {"games": 1035, "rating": 2246, "rd": 45, "prog": -11}, "kingOfTheHill": {"games": 2, "rating": 2058, "rd": 304, "prog": 0, "prov": true}, "crazyhouse": {"games": 1, "rating": 1741, "rd": 396, "prog": 0, "prov": true}, "threeCheck": {"games": 1, "rating": 1625, "rd": 352, "prog": 0, "prov": true}, "bullet": {"games": 2347, "rating": 2353, "rd": 45, "prog": 27}, "correspondence": {"games": 0, "rating": 1500, "rd": 500, "prog": 0, "prov": true}, "horde": {"games": 2, "rating": 1481, "rd": 270, "prog": 0, "prov": true}, "puzzle": {"games": 238, "rating": 2585, "rd": 68, "prog": 0}, "classical": {"games": 0, "rating": 1500, "rd": 500, "prog": 0, "prov": true}, "rapid": {"games": 12, "rating": 1789, "rd": 145, "prog": 48, "prov": true}, "storm": {"runs": 55, "score": 71}}, "createdAt": 1586994835070, "profile": {"country": "AM", "firstName": "Susanna", "lastName": "Gaboyan", "fideRating": 2211, "links": "https://www.instagram.com/susik_gaboyan/\r\nhttps://www.twitch.tv/susikgaboyan"}, "seenAt": 1612476478509, "playTime": {"total": 758280, "tv": 1301}, "language": "en-US", "title": "WIM", "url": "https://lichess.org/@/Susik_Gaboyan", "playing": "https://lichess.org/r6bJvN00/white", "nbFollowing": 12, "nbFollowers": 216, "completionRate": 90, "count": {"all": 3974, "rated": 3456, "ai": 0, "draw": 200, "drawH": 200, "loss": 1702, "lossH": 1702, "win": 2072, "winH": 2072, "bookmark": 0, "playing": 1, "import": 0, "me": 0}, "streaming": true}, {"id": "gnoraz", "username": "Gnoraz", "online": true, "perfs": {"blitz": {"games": 1, "rating": 1343, "rd": 307, "prog": 0, "prov": true}, "puzzle": {"games": 473, "rating": 1684, "rd": 77, "prog": 0}, "bullet": {"games": 1, "rating": 1085, "rd": 314, "prog": 0, "prov": true}, "correspondence": {"games": 10, "rating": 1619, "rd": 171, "prog": 0, "prov": true}, "classical": {"games": 50, "rating": 1193, "rd": 65, "prog": 12}, "rapid": {"games": 134, "rating": 1043, "rd": 45, "prog": -17}, "storm": {"runs": 47, "score": 16}}, "createdAt": 1609284616571, "profile": {"country": "DE", "links": "twitch.tv/gnoraz\r\ntwitter.com/gnoraztheorc"}, "seenAt": 1612476812870, "playTime": {"total": 281069, "tv": 0}, "language": "de-DE", "url": "https://lichess.org/@/Gnoraz", "playing": "https://lichess.org/pi81UbkS/black", "nbFollowing": 0, "nbFollowers": 16, "completionRate": 100, "count": {"all": 266, "rated": 196, "ai": 0, "draw": 10, "drawH": 10, "loss": 148, "lossH": 148, "win": 108, "winH": 108, "bookmark": 0, "playing": 1, "import": 1, "me": 0}, "streaming": true}, {"id": "jurisdoctor", "username": "JurisDoctor", "online": true, "perfs": {"blitz": {"games": 1, "rating": 1473, "rd": 466, "prog": 0, "prov": true}, "puzzle": {"games": 383, "rating": 2114, "rd": 75, "prog": 0}, "ultraBullet": {"games": 4303, "rating": 1858, "rd": 45, "prog": 7}, "bullet": {"games": 0, "rating": 1500, "rd": 500, "prog": 0, "prov": true}, "correspondence": {"games": 0, "rating": 1500, "rd": 500, "prog": 0, "prov": true}, "classical": {"games": 0, "rating": 1500, "rd": 500, "prog": 0, "prov": true}, "rapid": {"games": 0, "rating": 1500, "rd": 500, "prog": 0, "prov": true}}, "createdAt": 1588642843446, "profile": {"country": "US", "location": "Classified", "bio": "Just someone who loves to play ultrabullet (exclusively with mouse). \r\n\r\nI <3 lichess\r\n\r\ni <3 techno.\r\n\r\noh, and I stream from time to time—\r\n\r\nCheck out my stream, and feel free to follow ;)\r\n\r\nNote: I am the one and the only JurisDoctor (other accounts with different configurations of this username are not me)", "links": "https://www.twitch.tv/jurisdoctorchess"}, "seenAt": 1612476409469, "playTime": {"total": 244842, "tv": 38027}, "language": "en-US", "url": "https://lichess.org/@/JurisDoctor", "playing": "https://lichess.org/T2kJMdwO/black", "nbFollowing": 88, "nbFollowers": 80, "completionRate": 97, "count": {"all": 6006, "rated": 4304, "ai": 12, "draw": 127, "drawH": 127, "loss": 2130, "lossH": 2118, "win": 3749, "winH": 3749, "bookmark": 0, "playing": 1, "import": 0, "me": 0}, "streaming": true}, {"id": "knottable", "username": "knottable", "online": true, "perfs": {"antichess": {"games": 1, "rating": 1440, "rd": 304, "prog": 0, "prov": true}, "atomic": {"games": 1, "rating": 1410, "rd": 278, "prog": 0, "prov": true}, "racingKings": {"games": 7, "rating": 1545, "rd": 219, "prog": 0, "prov": true}, "ultraBullet": {"games": 130, "rating": 849, "rd": 67, "prog": -9}, "blitz": {"games": 3162, "rating": 1421, "rd": 45, "prog": 22}, "threeCheck": {"games": 1, "rating": 1417, "rd": 282, "prog": 0, "prov": true}, "bullet": {"games": 1686, "rating": 1281, "rd": 47, "prog": -54}, "correspondence": {"games": 16, "rating": 1397, "rd": 130, "prog": 57, "prov": true}, "horde": {"games": 1, "rating": 1416, "rd": 282, "prog": 0, "prov": true}, "puzzle": {"games": 2241, "rating": 1732, "rd": 62, "prog": 0}, "classical": {"games": 293, "rating": 1524, "rd": 57, "prog": 48}, "rapid": {"games": 2012, "rating": 1505, "rd": 45, "prog": 45}, "storm": {"runs": 9, "score": 21}}, "createdAt": 1554683809348, "profile": {"country": "CA", "location": "Scarborough", "bio": "Send a challenge.... Or don't.\r\n\r\nI'm live on Twitch - Watch me at twitch.tv/knottable75", "firstName": "Agent", "lastName": "Smith", "links": "https://www.youtube.com/channel/UCc0FNUXh7ekB877GrRcHebQ\r\nhttps://discord.com/channels/717949678200815678/717949678640955455"}, "seenAt": 1612476705188, "playTime": {"total": 3262370, "tv": 3601}, "language": "en-US", "url": "https://lichess.org/@/knottable", "nbFollowing": 7, "nbFollowers": 71, "completionRate": 100, "count": {"all": 8213, "rated": 7311, "ai": 20, "draw": 454, "drawH": 454, "loss": 4473, "lossH": 4458, "win": 3286, "winH": 3281, "bookmark": 496, "playing": 0, "import": 1, "me": 0}, "streaming": true}, {"id": "lefonghua", "username": "lefonghua", "online": true, "perfs": {"blitz": {"games": 447, "rating": 2586, "rd": 45, "prog": 3}, "puzzle": {"games": 766, "rating": 3191, "rd": 170, "prog": 0, "prov": true}, "bullet": {"games": 253, "rating": 2530, "rd": 48, "prog": -41}, "correspondence": {"games": 0, "rating": 1500, "rd": 500, "prog": 0, "prov": true}, "classical": {"games": 0, "rating": 1500, "rd": 500, "prog": 0, "prov": true}, "rapid": {"games": 2, "rating": 2286, "rd": 296, "prog": 0, "prov": true}, "storm": {"runs": 3, "score": 73}}, "createdAt": 1602424612148, "profile": {"country": "CA", "location": "Montreal", "bio": "Professional Chess Coach & Twitch Streamer at twitch.tv/lefonghua\r\nInstagram: lefonghua", "firstName": "Lefong", "lastName": "Hua"}, "seenAt": 1612475630524, "playTime": {"total": 364424, "tv": 3196}, "language": "en-US", "title": "FM", "url": "https://lichess.org/@/lefonghua", "nbFollowing": 7, "nbFollowers": 609, "completionRate": 97, "count": {"all": 1505, "rated": 702, "ai": 3, "draw": 105, "drawH": 105, "loss": 365, "lossH": 365, "win": 1035, "winH": 1032, "bookmark": 0, "playing": 0, "import": 4, "me": 0}, "streaming": true}, {"id": "saintlouischessclub", "username": "SaintLouisChessClub", "online": true, "perfs": {"chess960": {"games": 247, "rating": 1899, "rd": 75, "prog": 4}, "antichess": {"games": 25, "rating": 1856, "rd": 120, "prog": 131, "prov": true}, "atomic": {"games": 49, "rating": 1902, "rd": 96, "prog": -116}, "racingKings": {"games": 9, "rating": 1589, "rd": 159, "prog": 0, "prov": true}, "ultraBullet": {"games": 51, "rating": 1784, "rd": 88, "prog": 11}, "blitz": {"games": 4237, "rating": 2166, "rd": 45, "prog": 3}, "kingOfTheHill": {"games": 29, "rating": 1791, "rd": 107, "prog": 84}, "crazyhouse": {"games": 19, "rating": 1830, "rd": 136, "prog": -68, "prov": true}, "threeCheck": {"games": 26, "rating": 1975, "rd": 97, "prog": -43}, "bullet": {"games": 810, "rating": 2174, "rd": 58, "prog": 0}, "correspondence": {"games": 1, "rating": 1662, "rd": 316, "prog": 0, "prov": true}, "horde": {"games": 32, "rating": 2042, "rd": 123, "prog": -38, "prov": true}, "puzzle": {"games": 1626, "rating": 2753, "rd": 84, "prog": 0}, "classical": {"games": 3, "rating": 1687, "rd": 250, "prog": 0, "prov": true}, "rapid": {"games": 213, "rating": 2176, "rd": 59, "prog": 21}, "storm": {"runs": 6, "score": 76}}, "createdAt": 1535639041780, "profile": {"country": "US", "location": "Saint Louis, Missouri, USA", "bio": "Our goals are to elevate the game of chess throughout the Saint Louis community and to introduce chess to thousands of Saint Louis’ children and adults.\r\n\r\nThis account will be used by multiple players", "links": "https://saintlouischessclub.org\r\nhttps://www.youtube.com/c/STLChessClub\r\nhttps://www.twitch.tv/stlchessclub\r\nhttps://twitter.com/stlchessclub\r\nhttps://www.instagram.com/stlchessclub\r\nhttps://uschesschamps.com\r\nhttps://grandchesstour.org"}, "seenAt": 1612476269241, "playTime": {"total": 3065815, "tv": 24427}, "language": "en-US", "title": "LM", "url": "https://lichess.org/@/SaintLouisChessClub", "playing": "https://lichess.org/37eUjp3L/white", "nbFollowing": 9, "nbFollowers": 4832, "completionRate": 72, "count": {"all": 7046, "rated": 5754, "ai": 13, "draw": 286, "drawH": 286, "loss": 1957, "lossH": 1947, "win": 4803, "winH": 4800, "bookmark": 1, "playing": 1, "import": 23, "me": 0}, "streaming": true}, {"id": "andy_rekt", "username": "andy_rekt", "online": true, "perfs": {"atomic": {"games": 2, "rating": 1241, "rd": 247, "prog": 0, "prov": true}, "blitz": {"games": 686, "rating": 2294, "rd": 45, "prog": -13}, "threeCheck": {"games": 1, "rating": 2015, "rd": 336, "prog": 0, "prov": true}, "bullet": {"games": 198, "rating": 2228, "rd": 53, "prog": 10}, "correspondence": {"games": 0, "rating": 1500, "rd": 500, "prog": 0, "prov": true}, "horde": {"games": 2, "rating": 1895, "rd": 240, "prog": 0, "prov": true}, "puzzle": {"games": 59, "rating": 2685, "rd": 118, "prog": 0, "prov": true}, "classical": {"games": 0, "rating": 1500, "rd": 500, "prog": 0, "prov": true}, "rapid": {"games": 1, "rating": 1474, "rd": 330, "prog": 0, "prov": true}, "storm": {"runs": 1, "score": 57}}, "createdAt": 1596825138853, "profile": {"country": "FR", "bio": "Hello everyone ! My name is Andreea Navrotescu, I am 23 yo and I am a professional French chess player. I am currently among top 5 women in France (FIDE April list). I have recently started streaming as well ! Do not hesitate to check my channel : twitch.tv/andy_rekt, it will be my pleasure to welcome you 💜. Have fun on Lichess !!!", "firstName": "Andreea", "lastName": "Navrotescu", "fideRating": 2284, "links": "twitch.tv/andy_rekt\r\nhttps://www.instagram.com/anavrotescu/\r\nhttps://twitter.com/andy_rekt_chess\r\nhttps://www.facebook.com/Andy_rekt-111062570576044"}, "seenAt": 1612475880282, "playTime": {"total": 645171, "tv": 222}, "language": "en-US", "title": "WIM", "url": "https://lichess.org/@/andy_rekt", "playing": "https://lichess.org/95ewFQAJ/white", "nbFollowing": 1, "nbFollowers": 501, "completionRate": 100, "count": {"all": 1080, "rated": 890, "ai": 4, "draw": 59, "drawH": 59, "loss": 439, "lossH": 438, "win": 582, "winH": 579, "bookmark": 0, "playing": 2, "import": 0, "me": 0}, "streaming": true}, {"id": "chaosismax", "username": "chaosismax", "online": true, "perfs": {"blitz": {"games": 25, "rating": 774, "rd": 79, "prog": -19}, "puzzle": {"games": 221, "rating": 1487, "rd": 82, "prog": 0}, "bullet": {"games": 0, "rating": 1500, "rd": 500, "prog": 0, "prov": true}, "correspondence": {"games": 0, "rating": 1500, "rd": 500, "prog": 0, "prov": true}, "classical": {"games": 0, "rating": 1500, "rd": 500, "prog": 0, "prov": true}, "rapid": {"games": 200, "rating": 1019, "rd": 45, "prog": -18}}, "createdAt": 1609022954294, "seenAt": 1612476645847, "playTime": {"total": 229625, "tv": 0}, "language": "en-US", "url": "https://lichess.org/@/chaosismax", "playing": "https://lichess.org/BhFV7K4u/black", "nbFollowing": 4, "nbFollowers": 10, "completionRate": 97, "count": {"all": 414, "rated": 225, "ai": 0, "draw": 12, "drawH": 12, "loss": 217, "lossH": 217, "win": 185, "winH": 185, "bookmark": 0, "playing": 1, "import": 0, "me": 0}, "streaming": true}, {"id": "willyjohnson", "username": "WillyJohnson", "online": true, "perfs": {"chess960": {"games": 175, "rating": 1948, "rd": 50, "prog": 19}, "antichess": {"games": 15, "rating": 1482, "rd": 120, "prog": -81, "prov": true}, "atomic": {"games": 69, "rating": 1400, "rd": 88, "prog": 51}, "racingKings": {"games": 5, "rating": 1677, "rd": 198, "prog": 0, "prov": true}, "ultraBullet": {"games": 55, "rating": 1436, "rd": 77, "prog": 7}, "blitz": {"games": 2614, "rating": 2265, "rd": 47, "prog": -8}, "kingOfTheHill": {"games": 124, "rating": 1929, "rd": 62, "prog": 4}, "crazyhouse": {"games": 103, "rating": 1797, "rd": 63, "prog": -19}, "threeCheck": {"games": 1, "rating": 1192, "rd": 305, "prog": 0, "prov": true}, "bullet": {"games": 5250, "rating": 2122, "rd": 48, "prog": 3}, "correspondence": {"games": 15, "rating": 2171, "rd": 190, "prog": -35, "prov": true}, "horde": {"games": 1, "rating": 1260, "rd": 356, "prog": 0, "prov": true}, "puzzle": {"games": 418, "rating": 2274, "rd": 189, "prog": 109, "prov": true}, "classical": {"games": 109, "rating": 2204, "rd": 69, "prog": 61}, "rapid": {"games": 600, "rating": 2315, "rd": 45, "prog": -17}}, "createdAt": 1443493695157, "profile": {"country": "US", "bio": "* Received United States Chess Federation (USCF) norms-based Candidate Master (CM) title back in 2014.\r\n\r\n* Achieved a USCF rating floor of 2000 in August 2005.", "fideRating": 2007, "links": "https://www.twitch.tv/grandmasterbees"}, "seenAt": 1612476029241, "playTime": {"total": 1999721, "tv": 86340}, "language": "en-US", "url": "https://lichess.org/@/WillyJohnson", "playing": "https://lichess.org/YfsPG8dX/black", "nbFollowing": 2, "nbFollowers": 51, "completionRate": 100, "count": {"all": 9180, "rated": 9142, "ai": 7, "draw": 736, "drawH": 733, "loss": 2946, "lossH": 2943, "win": 5498, "winH": 5497, "bookmark": 0, "playing": 1, "import": 0, "me": 0}, "streaming": true}]